{
  "metadata": {
    "timestamp": "20250805_215900",
    "tickers": [
      "AAPL",
      "GOOGL",
      "MSFT"
    ],
    "time_to_expiry": 0.25
  },
  "market_data": {
    "mu": [
      0.06865827193840245,
      0.20061736717561232,
      0.24425186408122032
    ],
    "sigma": [
      0.27182135660246215,
      0.29561094019156875,
      0.22496665652785328
    ],
    "correlation": [
      [
        1.0,
        0.4585620651880439,
        0.5358708347992309
      ],
      [
        0.4585620651880439,
        1.0,
        0.5351847861579428
      ],
      [
        0.5358708347992309,
        0.5351847861579428,
        1.0
      ]
    ],
    "current_prices": [
      202.9199981689453,
      194.6699981689453,
      527.75
    ],
    "data_period": "2y",
    "data_shape": [
      501,
      3
    ],
    "start_date": "2023-08-07",
    "end_date": "2025-08-05"
  },
  "options": [
    {
      "ticker": "AAPL",
      "type": "call",
      "strike": 202.9199981689453,
      "current_price": 202.9199981689453,
      "moneyness": 1.0
    },
    {
      "ticker": "GOOGL",
      "type": "put",
      "strike": 194.6699981689453,
      "current_price": 194.6699981689453,
      "moneyness": 1.0
    },
    {
      "ticker": "MSFT",
      "type": "call",
      "strike": 527.75,
      "current_price": 527.75,
      "moneyness": 1.0
    }
  ],
  "solver_results": {
    "n_assets": 3,
    "grid_size": [
      15,
      12,
      12
    ],
    "solve_time": 941.7574200630188,
    "validation_passed": true,
    "n_active_sets": 7,
    "max_value": 910.9810012817383,
    "parameters": {
      "mu_range": [
        0.06865827193840245,
        0.24425186408122032
      ],
      "sigma_range": [
        0.22496665652785328,
        0.29561094019156875
      ],
      "correlation_range": [
        0.4585620651880439,
        1.0
      ]
    }
  },
  "analysis": {
    "scenarios": [
      {
        "scenario": "Start",
        "time": 0.0,
        "wealth": 1.0,
        "value": 758.3142179854814,
        "stop_asset": null,
        "stop_ticker": null,
        "action": "Continue",
        "portfolio": [
          0.03333333333333333,
          0.03333333333333333,
          0.03333333333333333
        ]
      },
      {
        "scenario": "Mid-point",
        "time": 0.125,
        "wealth": 1.0,
        "value": 730.2693128455568,
        "stop_asset": null,
        "stop_ticker": null,
        "action": "Continue",
        "portfolio": [
          0.03333333333333333,
          0.03333333333333333,
          0.03333333333333333
        ]
      },
      {
        "scenario": "Near expiry",
        "time": 0.225,
        "wealth": 1.0,
        "value": 713.6495079613192,
        "stop_asset": null,
        "stop_ticker": null,
        "action": "Continue",
        "portfolio": [
          0.03333333333333333,
          0.03333333333333333,
          0.03333333333333333
        ]
      }
    ],
    "summary": {
      "n_assets": 3,
      "grid_size": [
        15,
        12,
        12
      ],
      "solve_time": 941.7574200630188,
      "validation_passed": true,
      "n_active_sets": 7,
      "max_value": 910.9810012817383,
      "parameters": {
        "mu_range": [
          0.06865827193840245,
          0.24425186408122032
        ],
        "sigma_range": [
          0.22496665652785328,
          0.29561094019156875
        ],
        "correlation_range": [
          0.4585620651880439,
          1.0
        ]
      }
    }
  },
  "simulations": {
    "n_simulations": 100,
    "n_successful": 100,
    "n_failed": 0,
    "wealth_statistics": {
      "mean": 10.681549733262427,
      "std": 26.91865595714541,
      "min": 1.0038201822973212,
      "max": 180.7609862206339,
      "median": 1.020658283871628,
      "q25": 1.0149962511388426,
      "q75": 1.0286188068239206
    },
    "stopping_frequencies": {
      "AAPL": {
        "count": 0,
        "frequency": 0.0
      },
      "GOOGL": {
        "count": 20,
        "frequency": 0.2
      },
      "MSFT": {
        "count": 2,
        "frequency": 0.02
      }
    },
    "successful_simulations": [
      {
        "simulation_id": 0,
        "final_wealth": 1.0076852902546927,
        "final_active_set": [
          0,
          1,
          2
        ],
        "stopping_decisions": [
          null,
          null,
          null,
          null,
          null,
          null,
          null,
          null,
          null,
          null,
          null,
          null,
          null,
          null,
          null,
          null,
          null,
          null,
          null,
          null,
          null,
          null,
          null,
          null,
          null,
          null,
          null,
          null,
          null,
          null,
          null,
          null,
          null,
          null,
          null,
          null,
          null,
          null,
          null,
          null,
          null,
          null,
          null,
          null,
          null,
          null,
          null,
          null,
          null
        ]
      },
      {
        "simulation_id": 1,
        "final_wealth": 1.0126275178975463,
        "final_active_set": [
          0,
          1,
          2
        ],
        "stopping_decisions": [
          null,
          null,
          null,
          null,
          null,
          null,
          null,
          null,
          null,
          null,
          null,
          null,
          null,
          null,
          null,
          null,
          null,
          null,
          null,
          null,
          null,
          null,
          null,
          null,
          null,
          null,
          null,
          null,
          null,
          null,
          null,
          null,
          null,
          null,
          null,
          null,
          null,
          null,
          null,
          null,
          null,
          null,
          null,
          null,
          null,
          null,
          null,
          null,
          null
        ]
      },
      {
        "simulation_id": 2,
        "final_wealth": 1.012180628050693,
        "final_active_set": [
          0,
          1,
          2
        ],
        "stopping_decisions": [
          null,
          null,
          null,
          null,
          null,
          null,
          null,
          null,
          null,
          null,
          null,
          null,
          null,
          null,
          null,
          null,
          null,
          null,
          null,
          null,
          null,
          null,
          null,
          null,
          null,
          null,
          null,
          null,
          null,
          null,
          null,
          null,
          null,
          null,
          null,
          null,
          null,
          null,
          null,
          null,
          null,
          null,
          null,
          null,
          null,
          null,
          null,
          null,
          null
        ]
      },
      {
        "simulation_id": 3,
        "final_wealth": 31.796496631042228,
        "final_active_set": [
          0,
          2
        ],
        "stopping_decisions": [
          null,
          null,
          null,
          null,
          null,
          null,
          null,
          null,
          null,
          null,
          null,
          null,
          null,
          null,
          null,
          null,
          null,
          null,
          null,
          null,
          null,
          null,
          null,
          null,
          null,
          null,
          null,
          null,
          null,
          null,
          null,
          null,
          null,
          null,
          null,
          null,
          null,
          null,
          null,
          null,
          1,
          null,
          null,
          null,
          null,
          null,
          null,
          null,
          null
        ]
      },
      {
        "simulation_id": 4,
        "final_wealth": 1.011741989190201,
        "final_active_set": [
          0,
          1,
          2
        ],
        "stopping_decisions": [
          null,
          null,
          null,
          null,
          null,
          null,
          null,
          null,
          null,
          null,
          null,
          null,
          null,
          null,
          null,
          null,
          null,
          null,
          null,
          null,
          null,
          null,
          null,
          null,
          null,
          null,
          null,
          null,
          null,
          null,
          null,
          null,
          null,
          null,
          null,
          null,
          null,
          null,
          null,
          null,
          null,
          null,
          null,
          null,
          null,
          null,
          null,
          null,
          null
        ]
      },
      {
        "simulation_id": 5,
        "final_wealth": 1.0196343822703327,
        "final_active_set": [
          0,
          1,
          2
        ],
        "stopping_decisions": [
          null,
          null,
          null,
          null,
          null,
          null,
          null,
          null,
          null,
          null,
          null,
          null,
          null,
          null,
          null,
          null,
          null,
          null,
          null,
          null,
          null,
          null,
          null,
          null,
          null,
          null,
          null,
          null,
          null,
          null,
          null,
          null,
          null,
          null,
          null,
          null,
          null,
          null,
          null,
          null,
          null,
          null,
          null,
          null,
          null,
          null,
          null,
          null,
          null
        ]
      },
      {
        "simulation_id": 6,
        "final_wealth": 1.0223844599811598,
        "final_active_set": [
          0,
          1,
          2
        ],
        "stopping_decisions": [
          null,
          null,
          null,
          null,
          null,
          null,
          null,
          null,
          null,
          null,
          null,
          null,
          null,
          null,
          null,
          null,
          null,
          null,
          null,
          null,
          null,
          null,
          null,
          null,
          null,
          null,
          null,
          null,
          null,
          null,
          null,
          null,
          null,
          null,
          null,
          null,
          null,
          null,
          null,
          null,
          null,
          null,
          null,
          null,
          null,
          null,
          null,
          null,
          null
        ]
      },
      {
        "simulation_id": 7,
        "final_wealth": 1.016600523934571,
        "final_active_set": [
          0,
          1,
          2
        ],
        "stopping_decisions": [
          null,
          null,
          null,
          null,
          null,
          null,
          null,
          null,
          null,
          null,
          null,
          null,
          null,
          null,
          null,
          null,
          null,
          null,
          null,
          null,
          null,
          null,
          null,
          null,
          null,
          null,
          null,
          null,
          null,
          null,
          null,
          null,
          null,
          null,
          null,
          null,
          null,
          null,
          null,
          null,
          null,
          null,
          null,
          null,
          null,
          null,
          null,
          null,
          null
        ]
      },
      {
        "simulation_id": 8,
        "final_wealth": 1.013480494336223,
        "final_active_set": [
          0,
          1,
          2
        ],
        "stopping_decisions": [
          null,
          null,
          null,
          null,
          null,
          null,
          null,
          null,
          null,
          null,
          null,
          null,
          null,
          null,
          null,
          null,
          null,
          null,
          null,
          null,
          null,
          null,
          null,
          null,
          null,
          null,
          null,
          null,
          null,
          null,
          null,
          null,
          null,
          null,
          null,
          null,
          null,
          null,
          null,
          null,
          null,
          null,
          null,
          null,
          null,
          null,
          null,
          null,
          null
        ]
      },
      {
        "simulation_id": 9,
        "final_wealth": 1.0101989259726802,
        "final_active_set": [
          0,
          1,
          2
        ],
        "stopping_decisions": [
          null,
          null,
          null,
          null,
          null,
          null,
          null,
          null,
          null,
          null,
          null,
          null,
          null,
          null,
          null,
          null,
          null,
          null,
          null,
          null,
          null,
          null,
          null,
          null,
          null,
          null,
          null,
          null,
          null,
          null,
          null,
          null,
          null,
          null,
          null,
          null,
          null,
          null,
          null,
          null,
          null,
          null,
          null,
          null,
          null,
          null,
          null,
          null,
          null
        ]
      }
    ],
    "failed_simulations": []
  }
}